fast_deskew/__init__.py
fast_deskew/deskew.py
fast_deskew-1.0.dist-info/METADATA
fast_deskew-1.0.dist-info/WHEEL
fast_deskew-1.0.dist-info/top_level.txt
fast_deskew-1.0.dist-info/RECORD
