Metadata-Version: 2.1
Name: fast_deskew
Version: 1.0
Summary: Deskew any images faster than ever
Home-page: https://github.com/Subhamp7/fast_deskew
Author: Subham Prasad
Author-email: subham306952@gmail.com
License: MIT
Keywords: python,deskew,open cv,skew
Platform: UNKNOWN
Classifier: License :: OSI Approved :: MIT License
Classifier: Programming Language :: Python :: 3.6
Classifier: Programming Language :: Python :: 3.7
Classifier: Programming Language :: Python :: 3.8
Classifier: Operating System :: Unix
Classifier: Operating System :: MacOS :: MacOS X
Classifier: Operating System :: Microsoft :: Windows
Classifier: Intended Audience :: Developers
Requires-Python: >=3
